common_veb/__init__.py
common_veb/selenium_client.py
common_veb-0.0.1.dist-info/LICENSE
common_veb-0.0.1.dist-info/METADATA
common_veb-0.0.1.dist-info/WHEEL
common_veb-0.0.1.dist-info/top_level.txt
common_veb-0.0.1.dist-info/RECORD
