Metadata-Version: 2.1
Name: common-veb
Version: 0.0.1
Summary: Package containing common code and reusable components for pipelines and dags
Author-email: pieter de petter <pieter.de.petter@veb.be>
License: Copyright 2022 VEB        
Project-URL: Homepage, https://vlaamsenergiebedrijf.visualstudio.com/Terra/_git/terra-etl?path=/common_code
Classifier: Programming Language :: Python :: 3
Classifier: License :: OSI Approved :: MIT License
Classifier: Operating System :: OS Independent
Requires-Python: >=3.7
License-File: LICENSE
